{
  "paper_id": "paper:20120674-venue-s0883769412000954-indd",
  "manifest": {
    "source_path": "papers/Shin_MRSBulletin_2012.pdf",
    "sha256": "82ba7c1fdc5df4dcbb0732567f8672143639707212d129f580e9c211c10c5909",
    "ingested_at": "2026-04-20T22:08:36Z"
  },
  "bibliography": {
    "doi": null,
    "title": "S0883769412000954.indd",
    "year": 2012,
    "authors": "0674",
    "venue": null
  },
  "pdf_path": "papers/Shin_MRSBulletin_2012.pdf",
  "extraction": {
    "text_path": "normalized/extracts/20120674-venue-s0883769412000954-indd_p1-2.txt",
    "quality": "good",
    "extracted_at": "2026-04-20T22:08:36Z",
    "text_preview_chars": 8000
  },
  "entities_mentioned": [],
  "claims": [],
  "wiki_path": "wiki/papers/20120674-venue-s0883769412000954-indd.md",
  "updated": "2026-04-20T22:08:36Z"
}
