{
  "paper_id": "paper:2017zheng-venue-research-2",
  "manifest": {
    "source_path": "papers/Zheng_Hong_ACS_AMI_ALD_2017_proof.pdf",
    "sha256": "d1104cabee2adf9233634acaad0d68d3a1940dba7e63817b58b9ab540b7ee91e",
    "ingested_at": "2026-04-20T22:08:36Z"
  },
  "bibliography": {
    "doi": null,
    "title": "research 1..9",
    "year": 2017,
    "authors": null,
    "venue": null
  },
  "pdf_path": "papers/Zheng_Hong_ACS_AMI_ALD_2017_proof.pdf",
  "extraction": {
    "text_path": "normalized/extracts/2017zheng-venue-research-2_p1-2.txt",
    "quality": "good",
    "extracted_at": "2026-04-20T22:08:36Z",
    "text_preview_chars": 8000
  },
  "entities_mentioned": [],
  "claims": [],
  "wiki_path": "wiki/papers/2017zheng-venue-research-2.md",
  "updated": "2026-04-20T22:08:36Z"
}
