{
  "paper_id": "paper:2026mirakhory-venue-paper-2",
  "manifest": {
    "source_path": "papers/Mirakhory_JCP_2026_Xe_I_II_galley.pdf",
    "sha256": "c3a6aa4df221979a9f416493f3f6253d06814420dca745d03471cd029b0ab190",
    "ingested_at": "2026-04-20T22:08:36Z"
  },
  "bibliography": {
    "doi": null,
    "title": null,
    "year": 2026,
    "authors": null,
    "venue": null
  },
  "pdf_path": "papers/Mirakhory_JCP_2026_Xe_I_II_galley.pdf",
  "extraction": {
    "text_path": "normalized/extracts/2026mirakhory-venue-paper-2_p1-2.txt",
    "quality": "partial",
    "extracted_at": "2026-04-20T22:08:36Z",
    "text_preview_chars": 2943
  },
  "entities_mentioned": [],
  "claims": [],
  "wiki_path": "wiki/papers/2026mirakhory-venue-paper-2.md",
  "updated": "2026-04-20T22:08:36Z"
}
